laptools/__init__.py
laptools/_util.py
laptools/clap.py
laptools/dynamic_lsap.py
laptools-0.1.8.dist-info/LICENSE
laptools-0.1.8.dist-info/METADATA
laptools-0.1.8.dist-info/WHEEL
laptools-0.1.8.dist-info/entry_points.txt
laptools-0.1.8.dist-info/top_level.txt
laptools-0.1.8.dist-info/RECORD
