Metadata-Version: 2.1
Name: laptools
Version: 0.1.8
Summary: Fast constrained linear assignment problem (CLAP) solvers
Home-page: https://github.com/jdmoorman/laptools
Author: Jacob Moorman
Author-email: jacob@moorman.me
License: MIT License
Keywords: laptools
Platform: UNKNOWN
Classifier: Development Status :: 3 - Alpha
Classifier: Intended Audience :: Science/Research 
Classifier: License :: OSI Approved :: MIT License
Classifier: Natural Language :: English
Classifier: Programming Language :: Python
Classifier: Programming Language :: Python :: 3
Classifier: Programming Language :: Python :: 3 :: Only
Classifier: Programming Language :: Python :: 3.6
Classifier: Programming Language :: Python :: 3.7
Classifier: Programming Language :: Python :: 3.8
Classifier: Topic :: Scientific/Engineering
Requires-Python: >=3.6
Requires-Dist: numpy
Requires-Dist: scipy
Provides-Extra: all
Requires-Dist: numpy ; extra == 'all'
Requires-Dist: scipy ; extra == 'all'
Requires-Dist: codecov ; extra == 'all'
Requires-Dist: pytest ; extra == 'all'
Requires-Dist: pytest-cov ; extra == 'all'
Requires-Dist: pytest-raises ; extra == 'all'
Requires-Dist: sphinx (==1.8.5) ; extra == 'all'
Requires-Dist: pytest-runner ; extra == 'all'
Requires-Dist: pre-commit ; extra == 'all'
Requires-Dist: bumpversion (>=0.5.3) ; extra == 'all'
Requires-Dist: ipython (>=7.5.0) ; extra == 'all'
Requires-Dist: tox (>=3.5.2) ; extra == 'all'
Requires-Dist: twine (>=1.13.0) ; extra == 'all'
Requires-Dist: wheel (>=0.33.1) ; extra == 'all'
Requires-Dist: altair ; extra == 'all'
Requires-Dist: jupyterlab ; extra == 'all'
Requires-Dist: matplotlib ; extra == 'all'
Provides-Extra: dev
Requires-Dist: codecov ; extra == 'dev'
Requires-Dist: pytest ; extra == 'dev'
Requires-Dist: pytest-cov ; extra == 'dev'
Requires-Dist: pytest-raises ; extra == 'dev'
Requires-Dist: sphinx (==1.8.5) ; extra == 'dev'
Requires-Dist: pytest-runner ; extra == 'dev'
Requires-Dist: pre-commit ; extra == 'dev'
Requires-Dist: bumpversion (>=0.5.3) ; extra == 'dev'
Requires-Dist: ipython (>=7.5.0) ; extra == 'dev'
Requires-Dist: tox (>=3.5.2) ; extra == 'dev'
Requires-Dist: twine (>=1.13.0) ; extra == 'dev'
Requires-Dist: wheel (>=0.33.1) ; extra == 'dev'
Provides-Extra: docs
Requires-Dist: sphinx (==1.8.5) ; extra == 'docs'
Provides-Extra: interactive
Requires-Dist: altair ; extra == 'interactive'
Requires-Dist: jupyterlab ; extra == 'interactive'
Requires-Dist: matplotlib ; extra == 'interactive'
Provides-Extra: setup
Requires-Dist: pytest-runner ; extra == 'setup'
Provides-Extra: test
Requires-Dist: codecov ; extra == 'test'
Requires-Dist: pytest ; extra == 'test'
Requires-Dist: pytest-cov ; extra == 'test'
Requires-Dist: pytest-raises ; extra == 'test'
